tyx/__init__.py
tyx-0.0.0a1.dist-info/WHEEL
tyx-0.0.0a1.dist-info/entry_points.txt
tyx-0.0.0a1.dist-info/METADATA
tyx-0.0.0a1.dist-info/RECORD
