Metadata-Version: 2.3
Name: tyx
Version: 0.0.0a1
Summary: This project is taken to defend against confusion with `ty`.
Author: Zanie Blue
Author-email: Zanie Blue <contact@zanie.dev>
Requires-Python: >=3.13
